{
  "heading": "LAG #94",
  "subheading": "",
  "telegram_message_id": 104,
  "date": "Thursday November 10th 2022",
  "content": [
    {
      "category": "‼️ SPECIAL INSIGHTS 👀",
      "entries": [
        {
          "caption": "powered by AppMagic.rocks 😎\nDid you know Riot Games mobile titles LoL: Wild Rift, TFT, and LoR pull in lifetime rev of $168M with 109M downloads?  Riot's been improving its monetization (rev per download) by a lotttt over the past 2 years from $0.07 in 2020 to $1.50 in 2022.",
          "url": ""
        }
      ]
    },
    {
      "category": "🔦 Spotlight 🌟",
      "entries": [
        {
          "caption": "A look at Riot Games to self-publish LoL and TFT in Southeast Asia",
          "url": "https://www.gamedeveloper.com/pc/riot-games-to-self-publish-i-league-of-legends-i-and-i-teamfight-tactics-i-in-southeast-asia"
        }
      ]
    },
    {
      "category": "🌊 MARKET ☎️",
      "entries": [
        {
          "caption": "A look at Griffin Gaming Partners putting 30% of investments into women-run game startups",
          "url": "https://venturebeat.com/games/griffin-gaming-partners-has-put-30-of-its-investments-into-women-run-game-startups/"
        },
        {
          "caption": "A look at Unity's latest financials .  Q3 2022 revenue $322.9M",
          "url": "https://www.pocketgamer.biz/news/80153/unitys-latest-financials-reveal-3229-million-in-q3-2022-revenue-and-predict-q4-earnings/"
        },
        {
          "caption": "A look at Bandai Namco H1 sales above expectations. Revenue $3.2B (up 21% YoY)",
          "url": "https://www.gamesindustry.biz/bandai-namco-h1-sales-rise-above-expectations"
        },
        {
          "caption": "A look at AppLovin Q3 2022 rev hit $713M",
          "url": "https://mobilegamer.biz/applovin-revenue-hit-by-project-makeover-matchington-mansion-declines/"
        }
      ]
    },
    {
      "category": "🌈 Platforms 🏔",
      "entries": [
        {
          "caption": "A look at Riot Games to self-publish LoL and TFT in Southeast Asia",
          "url": "https://www.gamedeveloper.com/pc/riot-games-to-self-publish-i-league-of-legends-i-and-i-teamfight-tactics-i-in-southeast-asia"
        },
        {
          "caption": "A look at TikTok being impacted by ATT by @eric_seufert",
          "url": "https://mobiledevmemo.com/of-course-tiktok-is-impacted-by-att/"
        }
      ]
    },
    {
      "category": "✨ Web 3️⃣ + Meta 🌎",
      "entries": [
        {
          "caption": "A look at Andrew Chen (GP of a16z Games) takes on why building the metaverse is hard @andrewchen",
          "url": "https://twitter.com/andrewchen/status/1590874178156392457"
        },
        {
          "caption": "A look at the damage to web3 gaming from FTX's collapse",
          "url": "https://superjoost.substack.com/p/house-of-crypto?utm_source=substack&utm_medium=email"
        },
        {
          "caption": "A look at Polygon working w/ Disney Accelerator @fwiz",
          "url": "https://twitter.com/Fwiz/status/1590864364470693889"
        },
        {
          "caption": "A look at DigiDaigaku collab with My Pet Hooligan.  @gabrielleydon @mypethooligan @digidaigaku",
          "url": "https://twitter.com/gabrielleydon/status/1590836064775974912"
        },
        {
          "caption": "A look at FIFA's future games being \"future-focused\" blockchain games",
          "url": "https://www.gamedeveloper.com/business/fifa-s-first-post-ea-games-will-be-future-focused-blockchaingames"
        },
        {
          "caption": "A look at Sorare partnering with 18 national teams",
          "url": "https://venturebeat.com/games/sorare-partners-with-18-national-soccer-teams-launches-game/"
        }
      ]
    }
  ],
  "number": 94
}